setup.py
django_testtools/__init__.py
django_testtools/client.py
django_testtools/settingsmanager.py
django_testtools/test.py
django_testtools.egg-info/PKG-INFO
django_testtools.egg-info/SOURCES.txt
django_testtools.egg-info/dependency_links.txt
django_testtools.egg-info/requires.txt
django_testtools.egg-info/top_level.txt