Metadata-Version: 1.0
Name: django-testtools
Version: 0.1
Summary: A helper for writting Django's tests
Home-page: http://github.com/dekode/django-testtools
Author: Bernardo Fontes
Author-email: falecomigo@bernardofontes.net
License: http://www.gnu.org/licenses/lgpl.html
Keywords: django testing
Platform: UNKNOWN
